datasette_glitch/__init__.py
datasette_glitch-0.1.dist-info/METADATA
datasette_glitch-0.1.dist-info/WHEEL
datasette_glitch-0.1.dist-info/entry_points.txt
datasette_glitch-0.1.dist-info/top_level.txt
datasette_glitch-0.1.dist-info/RECORD
