Metadata-Version: 2.1
Name: datasette-glitch
Version: 0.1
Summary: Utilities to help run Datasette on Glitch
Home-page: https://github.com/simonw/datasette-glitch
Author: Simon Willison
License: Apache License, Version 2.0
Project-URL: Issues, https://github.com/simonw/datasette-glitch/issues
Project-URL: CI, https://github.com/simonw/datasette-glitch/actions
Project-URL: Changelog, https://github.com/simonw/datasette-glitch/releases
Platform: UNKNOWN
Requires-Dist: datasette (>=0.45)
Provides-Extra: test
Requires-Dist: pytest ; extra == 'test'
Requires-Dist: pytest-asyncio ; extra == 'test'
Requires-Dist: httpx ; extra == 'test'
